ryd_client/__init__.py
ryd_client/ryd_client.py
ryd_client-0.0.6.dist-info/LICENSE
ryd_client-0.0.6.dist-info/METADATA
ryd_client-0.0.6.dist-info/WHEEL
ryd_client-0.0.6.dist-info/top_level.txt
ryd_client-0.0.6.dist-info/RECORD
