Metadata-Version: 2.1
Name: ryd-client
Version: 0.0.6
Summary: api client for returnyoutubedislike.com
Home-page: https://github.com/bbilly1/ryd-client
Author: Simon
Author-email: simobilleter@gmail.com
Project-URL: Bug Tracker, https://github.com/bbilly1/ryd-client/issues
Classifier: Programming Language :: Python :: 3
Classifier: License :: OSI Approved :: MIT License
Classifier: Operating System :: OS Independent
Requires-Python: >=3.6
License-File: LICENSE
Requires-Dist: requests
